FLiESANN/ECOv002-cal-val-FLiESANN-inputs.csv
FLiESANN/ECOv002-cal-val-FLiESANN-outputs.csv
FLiESANN/ECOv002-static-tower-FLiESANN-inputs.csv
FLiESANN/ECOv002_calval_FLiESANN_GEOS5FP_inputs.csv
FLiESANN/ECOv002_calval_FLiESANN_inputs.py
FLiESANN/ECOv002_calval_FLiESANN_outputs.py
FLiESANN/ECOv002_static_tower_FLiESANN_inputs.py
FLiESANN/FLiESANN.h5
FLiESANN/FLiESANN.py
FLiESANN/__init__.py
FLiESANN/colors.py
FLiESANN/constants.py
FLiESANN/determine_atype.py
FLiESANN/determine_ctype.py
FLiESANN/ensure_array.py
FLiESANN/filter_dataframe_to_location_time_pairs.py
FLiESANN/generate_FLiESANN_GEOS5FP_inputs.py
FLiESANN/generate_FLiESANN_inputs_table.py
FLiESANN/generate_FLiESANN_inputs_table_deprecated.py
FLiESANN/generate_input_dataset.py
FLiESANN/generate_output_dataset.py
FLiESANN/generate_static_input_dataset.py
FLiESANN/load_FLiESANN_model.py
FLiESANN/partition_spectral_albedo_with_NDVI.py
FLiESANN/prepare_FLiESANN_inputs.py
FLiESANN/process_FLiESANN.py
FLiESANN/process_FLiESANN_table.py
FLiESANN/retrieve_FLiESANN_GEOS5FP_inputs.py
FLiESANN/retrieve_FLiESANN_inputs.py
FLiESANN/retrieve_FLiESANN_static_inputs.py
FLiESANN/run_FLiESANN_inference.py
FLiESANN/verify.py
FLiESANN/version.py
fliesann-2.13.0.dist-info/licenses/LICENSE
tests/test_import_FLiESANN.py
tests/test_import_dependencies.py
tests/test_verify.py
fliesann-2.13.0.dist-info/METADATA
fliesann-2.13.0.dist-info/WHEEL
fliesann-2.13.0.dist-info/entry_points.txt
fliesann-2.13.0.dist-info/top_level.txt
fliesann-2.13.0.dist-info/RECORD
