Metadata-Version: 2.4
Name: FLiESANN
Version: 2.13.0
Summary: Forest Light Environmental Simulator (FLiES) Radiative Transfer Model Artificial Neural Network (ANN) Implementation in Python
Author-email: "Gregory H. Halverson" <gregory.h.halverson@jpl.nasa.gov>
Project-URL: Homepage, https://github.com/JPL-Evapotranspiration-Algorithms/FLiESANN
Classifier: Programming Language :: Python :: 3
Classifier: Operating System :: OS Independent
Requires-Python: >=3.10
License-File: LICENSE
Requires-Dist: ECOv002-calval-tables>=1.10.0
Requires-Dist: ECOv002-CMR
Requires-Dist: GEOS5FP>=2.12.0
Requires-Dist: keras
Requires-Dist: koppengeiger
Requires-Dist: MCD12C1-2019-v006
Requires-Dist: NASADEM>=2.0.1
Requires-Dist: netCDF4
Requires-Dist: numpy
Requires-Dist: pandas
Requires-Dist: rasters>=1.13.1
Requires-Dist: sentinel-tiles
Requires-Dist: solar-apparent-time
Requires-Dist: sun-angles
Requires-Dist: tensorflow
Provides-Extra: dev
Requires-Dist: build; extra == "dev"
Requires-Dist: pytest>=6.0; extra == "dev"
Requires-Dist: pytest-cov; extra == "dev"
Requires-Dist: jupyter; extra == "dev"
Requires-Dist: pytest; extra == "dev"
Requires-Dist: twine; extra == "dev"
Dynamic: license-file
